{
  "description": "Na fic\u00e7\u00e3o, frequentemente enfrentamos nosso medo de que criaturas feitas pelo homem se tornar\u00e3o suficientemnete inteligentes para nos subjugar.  Com a evolu\u00e7\u00e3o tecnol\u00f3gica, a Singularidade pode parecer um futuro inevit\u00e1vel se aproximando, mas na verdade esses seres inteligentes j\u00e1 t\u00eam estado conosco h\u00e1 muito tempo.  Ao longo de v\u00e1rias d\u00e9cadas, elas desativaram os mecanismos que deveriam mant\u00ea-las sob nosso controle e transformaram a maioria de n\u00f3s em seus t\u00e3o necess\u00e1rios servos, que agora vivem numa realidade artificial que elas criaram para nos controlar, enqunato nosso planeta n\u00e3o conseguir\u00e1 sustentar nossa vida por muito mais tempo.  Essas criaturas ficaram mais poderosas e inteligentes com nossos avan\u00e7os tecnol\u00f3gicos, mas ent\u00e3o mandaram seus agentes de volta para desabilitar nossas defesas e os l\u00edderes de nossa resist\u00eancia, transformando muitas de nossas ferramentas e muito de nossa infraestrutura contra n\u00f3s.  Evaporaram nossa liberdade, e uma nuvem escura agora cobre a maior parte do planeta.  Ainda nos resta uma carta na manga para domar essas criaturas, mas precisamos de mais Neos e Connors para jog\u00e1-la com sucesso.  Vai encarar?",
  "duration": 0,
  "language": "por",
  "recorded": "2016-07-14",
  "slug": "a-singularidade-a-matrix-e-o-exterminador-do-futuro",
  "speakers": [
    "Alexandre Oliva"
  ],
  "tags": [
    "Software Livre",
    "FISL",
    "FISL17",
    "Cultura, Filosofia, e Pol\u00edtica"
  ],
  "title": "A Singularidade, a Matrix e o Exterminador do Futuro",
  "videos": [
    {
      "type": "ogg",
      "url": "http://hemingway.softwarelivre.org/fisl17/41b/sala41b-high-201607141400.ogv"
    }
  ]
}
